{"node":{"36bc73ad38d694c579e3598bd450a2a6029f558c":{"workers":{"app/page":47107,"app/_not-found":73199,"app/pages/login/page":73199,"app/pages/products/[id]/page":73199,"app/pages/products/add/page":73199,"app/pages/products/page":73199,"app/pages/projects/[id]/page":73199,"app/pages/projects/create/page":73199,"app/pages/projects/page":73199,"app/pages/users/[userId]/page":73199,"app/pages/register/page":73199,"app/pages/users/page":73199},"layer":{"app/page":"rsc","app/_not-found":"action-browser","app/pages/login/page":"action-browser","app/pages/products/[id]/page":"action-browser","app/pages/products/add/page":"action-browser","app/pages/products/page":"action-browser","app/pages/projects/[id]/page":"action-browser","app/pages/projects/create/page":"action-browser","app/pages/projects/page":"action-browser","app/pages/users/[userId]/page":"action-browser","app/pages/register/page":"action-browser","app/pages/users/page":"action-browser"}},"78b55bdabf88dcd5be651d7a1d785fc3ec43e204":{"workers":{"app/page":47107,"app/_not-found":73199,"app/pages/login/page":73199,"app/pages/products/[id]/page":73199,"app/pages/products/add/page":73199,"app/pages/products/page":73199,"app/pages/projects/[id]/page":73199,"app/pages/projects/create/page":73199,"app/pages/projects/page":73199,"app/pages/users/[userId]/page":73199,"app/pages/register/page":73199,"app/pages/users/page":73199},"layer":{"app/page":"rsc","app/_not-found":"action-browser","app/pages/login/page":"action-browser","app/pages/products/[id]/page":"action-browser","app/pages/products/add/page":"action-browser","app/pages/products/page":"action-browser","app/pages/projects/[id]/page":"action-browser","app/pages/projects/create/page":"action-browser","app/pages/projects/page":"action-browser","app/pages/users/[userId]/page":"action-browser","app/pages/register/page":"action-browser","app/pages/users/page":"action-browser"}},"7d54574caa5baa2b96b25e4c0991e44adb146ad5":{"workers":{"app/page":47107,"app/_not-found":73199,"app/pages/login/page":73199,"app/pages/products/[id]/page":73199,"app/pages/products/add/page":73199,"app/pages/products/page":73199,"app/pages/projects/[id]/page":73199,"app/pages/projects/create/page":73199,"app/pages/projects/page":73199,"app/pages/users/[userId]/page":73199,"app/pages/register/page":73199,"app/pages/users/page":73199},"layer":{"app/page":"rsc","app/_not-found":"action-browser","app/pages/login/page":"action-browser","app/pages/products/[id]/page":"action-browser","app/pages/products/add/page":"action-browser","app/pages/products/page":"action-browser","app/pages/projects/[id]/page":"action-browser","app/pages/projects/create/page":"action-browser","app/pages/projects/page":"action-browser","app/pages/users/[userId]/page":"action-browser","app/pages/register/page":"action-browser","app/pages/users/page":"action-browser"}},"a089af096e473eb392bf8f455b8df460c2759fc8":{"workers":{"app/page":47107,"app/_not-found":73199,"app/pages/login/page":73199,"app/pages/products/[id]/page":73199,"app/pages/products/add/page":73199,"app/pages/products/page":73199,"app/pages/projects/[id]/page":73199,"app/pages/projects/create/page":73199,"app/pages/projects/page":73199,"app/pages/users/[userId]/page":73199,"app/pages/register/page":73199,"app/pages/users/page":73199},"layer":{"app/page":"rsc","app/_not-found":"action-browser","app/pages/login/page":"action-browser","app/pages/products/[id]/page":"action-browser","app/pages/products/add/page":"action-browser","app/pages/products/page":"action-browser","app/pages/projects/[id]/page":"action-browser","app/pages/projects/create/page":"action-browser","app/pages/projects/page":"action-browser","app/pages/users/[userId]/page":"action-browser","app/pages/register/page":"action-browser","app/pages/users/page":"action-browser"}},"b17d8f6613e66b3cb3357cbd972b101329bd0326":{"workers":{"app/page":47107,"app/_not-found":73199,"app/pages/login/page":73199,"app/pages/products/[id]/page":73199,"app/pages/products/add/page":73199,"app/pages/products/page":73199,"app/pages/projects/[id]/page":73199,"app/pages/projects/create/page":73199,"app/pages/projects/page":73199,"app/pages/users/[userId]/page":73199,"app/pages/register/page":73199,"app/pages/users/page":73199},"layer":{"app/page":"rsc","app/_not-found":"action-browser","app/pages/login/page":"action-browser","app/pages/products/[id]/page":"action-browser","app/pages/products/add/page":"action-browser","app/pages/products/page":"action-browser","app/pages/projects/[id]/page":"action-browser","app/pages/projects/create/page":"action-browser","app/pages/projects/page":"action-browser","app/pages/users/[userId]/page":"action-browser","app/pages/register/page":"action-browser","app/pages/users/page":"action-browser"}},"edc9d95c9d80edb936c64090b673fa63c7fdb0c3":{"workers":{"app/page":47107,"app/_not-found":73199,"app/pages/login/page":73199,"app/pages/products/[id]/page":73199,"app/pages/products/add/page":73199,"app/pages/products/page":73199,"app/pages/projects/[id]/page":73199,"app/pages/projects/create/page":73199,"app/pages/projects/page":73199,"app/pages/users/[userId]/page":73199,"app/pages/register/page":73199,"app/pages/users/page":73199},"layer":{"app/page":"rsc","app/_not-found":"action-browser","app/pages/login/page":"action-browser","app/pages/products/[id]/page":"action-browser","app/pages/products/add/page":"action-browser","app/pages/products/page":"action-browser","app/pages/projects/[id]/page":"action-browser","app/pages/projects/create/page":"action-browser","app/pages/projects/page":"action-browser","app/pages/users/[userId]/page":"action-browser","app/pages/register/page":"action-browser","app/pages/users/page":"action-browser"}}},"edge":{},"encryptionKey":"8RfE4oxfcVTojLhCmIoRMTzOmP5wa2AZXB63GHvmrTA="}